colorbrewer/__init__.py
colorbrewer/data/ColorBrewer_all_schemes_RGBonly3.csv
colorbrewer/data/__init__.py
colorbrewer-0.3.dist-info/LICENSE
colorbrewer-0.3.dist-info/METADATA
colorbrewer-0.3.dist-info/WHEEL
colorbrewer-0.3.dist-info/top_level.txt
colorbrewer-0.3.dist-info/RECORD
